ezsaver/__init__.py
ezsaver/ezsaver.py
ezsaver-0.1.0.dist-info/LICENSE.md
ezsaver-0.1.0.dist-info/METADATA
ezsaver-0.1.0.dist-info/WHEEL
ezsaver-0.1.0.dist-info/top_level.txt
ezsaver-0.1.0.dist-info/RECORD
