Metadata-Version: 2.1
Name: ezsaver
Version: 0.1.0
Summary: Save stuff quick and easy in Python
Home-page: https://github.com/EricThomson/ezsaver
Author: Eric Thomson
Author-email: thomson.eric@gmail.com
License: MIT
License-File: LICENSE.md
Requires-Dist: joblib
Requires-Dist: varname
